{
  "version": "7",
  "dialect": "postgresql",
  "entries": [
    {
      "idx": 0,
      "version": "7",
      "when": 1779414338899,
      "tag": "0000_wealthy_pixie",
      "breakpoints": true
    },
    {
      "idx": 1,
      "version": "7",
      "when": 1779414987258,
      "tag": "0001_illegal_gwen_stacy",
      "breakpoints": true
    },
    {
      "idx": 2,
      "version": "7",
      "when": 1779416146329,
      "tag": "0002_organic_satana",
      "breakpoints": true
    },
    {
      "idx": 3,
      "version": "7",
      "when": 1779732300617,
      "tag": "0003_overjoyed_johnny_blaze",
      "breakpoints": true
    },
    {
      "idx": 4,
      "version": "7",
      "when": 1779771551622,
      "tag": "0004_silly_gorgon",
      "breakpoints": true
    },
    {
      "idx": 5,
      "version": "7",
      "when": 1779780418380,
      "tag": "0005_wealthy_whizzer",
      "breakpoints": true
    },
    {
      "idx": 6,
      "version": "7",
      "when": 1779782533735,
      "tag": "0006_unknown_quasimodo",
      "breakpoints": true
    },
    {
      "idx": 7,
      "version": "7",
      "when": 1779805524793,
      "tag": "0007_certain_thunderbolts",
      "breakpoints": true
    },
    {
      "idx": 8,
      "version": "7",
      "when": 1779808021477,
      "tag": "0008_premium_lake",
      "breakpoints": true
    },
    {
      "idx": 9,
      "version": "7",
      "when": 1779808500000,
      "tag": "0009_drop_payments_dup_fk",
      "breakpoints": true
    },
    {
      "idx": 10,
      "version": "7",
      "when": 1779868800000,
      "tag": "0010_dotfy_migration",
      "breakpoints": true
    },
    {
      "idx": 11,
      "version": "7",
      "when": 1779869000000,
      "tag": "0011_dotfy_product_columns",
      "breakpoints": true
    },
    {
      "idx": 12,
      "version": "7",
      "when": 1780079537389,
      "tag": "0012_old_nekra",
      "breakpoints": true
    },
    {
      "idx": 13,
      "version": "7",
      "when": 1780079850605,
      "tag": "0013_chemical_chimera",
      "breakpoints": true
    }
  ]
}